int2az/__init__.py
int2az-0.2.dist-info/DESCRIPTION.rst
int2az-0.2.dist-info/METADATA
int2az-0.2.dist-info/RECORD
int2az-0.2.dist-info/WHEEL
int2az-0.2.dist-info/metadata.json
int2az-0.2.dist-info/top_level.txt
