Metadata-Version: 2.0
Name: int2az
Version: 0.2
Summary: Utility for translating numbers into Azerbaijani
Home-page: https://github.com/0rang3max/int2az
Author: Maxim Semenov
Author-email: 0rang3max@gmail.com
License: UNKNOWN
Keywords: az int2str
Platform: UNKNOWN
Classifier: Development Status :: 3 - Alpha
Classifier: Intended Audience :: Developers
Classifier: Topic :: Software Development :: Build Tools
Classifier: License :: OSI Approved :: MIT License
Classifier: Programming Language :: Python :: 3
Classifier: Programming Language :: Python :: 3.4
Classifier: Programming Language :: Python :: 3.5
Classifier: Programming Language :: Python :: 3.6
